intelab_python_sdk/__init__.py
intelab_python_sdk/utils.py
intelab_python_sdk/cache/__init__.py
intelab_python_sdk/cache/file_system_cache.py
intelab_python_sdk/dingtalk/__init__.py
intelab_python_sdk/email/__init__.py
intelab_python_sdk/ffmpeg/__init__.py
intelab_python_sdk/ffmpeg/ffmpeg_capture.py
intelab_python_sdk/ffmpeg/ffmpeg_concat.py
intelab_python_sdk/ffmpeg/ffmpeg_mp4tomp3.py
intelab_python_sdk/ffmpeg/ffmpeg_prune.py
intelab_python_sdk/ffmpeg/ffmpeg_read_frames.py
intelab_python_sdk/ffmpeg/ffmpeg_record.py
intelab_python_sdk/ffmpeg/ffmpeg_utils.py
intelab_python_sdk/helper/__init__.py
intelab_python_sdk/helper/cpu.py
intelab_python_sdk/logger/__init__.py
intelab_python_sdk/logger/timerotaingfilehandler.py
intelab_python_sdk-0.7.4.dist-info/LICENSE
intelab_python_sdk-0.7.4.dist-info/METADATA
intelab_python_sdk-0.7.4.dist-info/WHEEL
intelab_python_sdk-0.7.4.dist-info/entry_points.txt
intelab_python_sdk-0.7.4.dist-info/top_level.txt
intelab_python_sdk-0.7.4.dist-info/RECORD
