Metadata-Version: 2.1
Name: intelab_python_sdk
Version: 0.7.4
Home-page: https://github.com/zwwangoo/intelab-python-sdk
Author: zwwangoo
Author-email: w_angzhiwen@163.com
Classifier: Programming Language :: Python :: 3.5
Classifier: Programming Language :: Python :: 3.6
Classifier: Programming Language :: Python :: 3.7
Classifier: Programming Language :: Python :: 3.11
Requires-Python: >=3.5
License-File: LICENSE
